{"batchcomplete":"","query":{"geosearch":[{"pageid":56154,"ns":0,"title":"Sagrada Fam\u00edlia","lat":41.4034,"lon":2.17444,"dist":26.5,"primary":""},{"pageid":7065748,"ns":0,"title":"\u00c9cole de la Sagrada Fam\u00edlia","lat":41.402982,"lon":2.174212,"dist":73,"primary":""},{"pageid":9065945,"ns":0,"title":"Sagrada Fam\u00edlia (m\u00e9tro de Barcelone)","lat":41.404528,"lon":2.174492,"dist":100.5,"primary":""},{"pageid":5001240,"ns":0,"title":"Place de la Sagrada Fam\u00edlia","lat":41.402678,"lon":2.173211,"dist":142.5,"primary":""},{"pageid":3688003,"ns":0,"title":"Si\u00e8ge de Barcelone (1705)","lat":41.40194444,"lon":2.17138889,"dist":310.4,"primary":""},{"pageid":5608917,"ns":0,"title":"Journ\u00e9es de mai 1937 \u00e0 Barcelone","lat":41.4019,"lon":2.17139,"dist":313.4,"primary":""},{"pageid":12174265,"ns":0,"title":"Place Pablo Neruda (Barcelone)","lat":41.401897222222,"lon":2.1786777777778,"dist":408.7,"primary":""},{"pageid":9072679,"ns":0,"title":"Monumental (m\u00e9tro de Barcelone)","lat":41.400563,"lon":2.179399,"dist":541.5,"primary":""},{"pageid":8444025,"ns":0,"title":"Casa Macaya","lat":41.3998,"lon":2.16943,"dist":591.7,"primary":""},{"pageid":11717301,"ns":0,"title":"Place Moss\u00e8n Jacint Verdaguer","lat":41.399139,"lon":2.16992,"dist":621.5,"primary":""}]}}